timeforge/__init__.py
timeforge/__main__.py
timeforge/config.py
timeforge/core.py
timeforge/gui.py
timeforge/helpers.py
timeforge/text_input.py
TimeForge-1.2.2.dist-info/LICENSE.md
TimeForge-1.2.2.dist-info/METADATA
TimeForge-1.2.2.dist-info/WHEEL
TimeForge-1.2.2.dist-info/entry_points.txt
TimeForge-1.2.2.dist-info/top_level.txt
TimeForge-1.2.2.dist-info/RECORD
