Metadata-Version: 2.2
Name: TimeForge
Version: 1.2.2
Summary: Create realistic looking but fake time documentation for your student job at KIT
Author-email: Michael Hohenstein <michael@hohenste.in>
Project-URL: Homepage, https://github.com/MitchiLaser/timeforge
Project-URL: Repository, https://github.com/MitchiLaser/timeforge
Classifier: Operating System :: OS Independent
Classifier: Programming Language :: Python :: 3
Classifier: Natural Language :: German
Classifier: Topic :: Office/Business
Classifier: Topic :: Office/Business :: Scheduling
Classifier: License :: OSI Approved :: GNU General Public License v3 (GPLv3)
Classifier: License :: OSI Approved :: GNU General Public License v3 or later (GPLv3+)
Requires-Python: >=3.7
License-File: LICENSE.md
Requires-Dist: argcomplete>=3.0.5
Requires-Dist: feiertage-de>=0.1.0
Requires-Dist: requests>=2.31.0
Requires-Dist: pypdf~=5.0
Requires-Dist: ConfigArgParse>=1.7
